.DS_Store
demyst/.DS_Store
demyst/analytics/.DS_Store
demyst/analytics/__init__.py
demyst/analytics/analytics.py
demyst/analytics/dummies.pickle
demyst/analytics/eprint.py
demyst/analytics/max_length.pickle
demyst/analytics/model.pickle
demyst/analytics/report.py
demyst/analytics/shiny.py
demyst/analytics/tokenizer.pickle
demyst/analytics/type_guesser.py
demyst/analytics/sample/website.csv
demyst_analytics-0.9.0.dist-info/METADATA
demyst_analytics-0.9.0.dist-info/WHEEL
demyst_analytics-0.9.0.dist-info/top_level.txt
demyst_analytics-0.9.0.dist-info/RECORD
