Metadata-Version: 2.1
Name: demyst-analytics
Version: 0.9.0
Author: Demyst Data
Author-email: info@demystdata.com
Requires-Dist: demyst-common (>=0.9.0)
Requires-Dist: yattag
Requires-Dist: IPython
Requires-Dist: tqdm
Requires-Dist: ipywidgets
Requires-Dist: pandas
Requires-Dist: pandas-schema
